{
    "date": "Fri May 26 22:16:35 UTC 2023",
    "context_size": "2048",
    "param_size": "65B",
    "model": "ggml-model-q4_0.bin",
    "ram_feeq": "3X00",
    "dimm_count": "4dimm",
    "governer": "schedutil",
    "concurrent_instance_count": 1,
    "load_time": [
        2345.09,
        2342.73,
        2343.93
    ],
    "sample_time": [
        0.32,
        0.31,
        0.32
    ],
    "prompt_eval_time": [
        788.24,
        790.01,
        793.31
    ],
    "eval_time": [
        925.21,
        926.84,
        937.35
    ],
    "total_time": [
        38446.47,
        38507.22,
        38918.5
    ],
    "threads": 4,
    "context": 2048,
    "load_time_mean": 2343.9166666666665,
    "load_time_median": 2343.93,
    "load_time_max": 2345.09,
    "load_time_min": 2342.73,
    "sample_time_mean": 0.31666666666666665,
    "sample_time_median": 0.32,
    "sample_time_max": 0.32,
    "sample_time_min": 0.31,
    "prompt_eval_time_mean": 790.52,
    "prompt_eval_time_median": 790.01,
    "prompt_eval_time_max": 793.31,
    "prompt_eval_time_min": 788.24,
    "eval_time_mean": 929.8000000000001,
    "eval_time_median": 926.84,
    "eval_time_max": 937.35,
    "eval_time_min": 925.21,
    "total_time_mean": 38624.06333333333,
    "total_time_median": 38507.22,
    "total_time_max": 38918.5,
    "total_time_min": 38446.47
}