{
    "date": "Wed May 31 05:57:58 UTC 2023",
    "context_size": "2048",
    "param_size": "7B",
    "model": "ggml-model-q4_0.bin",
    "ram_feeq": "5200",
    "dimm_count": "2dimm",
    "governer": "performance",
    "concurrent_instance_count": 3,
    "load_time": [
        281.3,
        358.32,
        370.09
    ],
    "sample_time": [
        0.33,
        0.33,
        0.33
    ],
    "prompt_eval_time": [
        111.99,
        129.51,
        131.95
    ],
    "eval_time": [
        191.33,
        186.68,
        181.55
    ],
    "total_time": [
        7762.55,
        4663.98,
        7469.49
    ],
    "threads": 9,
    "context": 2048,
    "load_time_mean": 336.57,
    "load_time_median": 358.32,
    "load_time_max": 370.09,
    "load_time_min": 281.3,
    "sample_time_mean": 0.33,
    "sample_time_median": 0.33,
    "sample_time_max": 0.33,
    "sample_time_min": 0.33,
    "prompt_eval_time_mean": 124.48333333333332,
    "prompt_eval_time_median": 129.51,
    "prompt_eval_time_max": 131.95,
    "prompt_eval_time_min": 111.99,
    "eval_time_mean": 186.52,
    "eval_time_median": 186.68,
    "eval_time_max": 191.33,
    "eval_time_min": 181.55,
    "total_time_mean": 6632.006666666666,
    "total_time_median": 7469.49,
    "total_time_max": 7762.55,
    "total_time_min": 4663.98
}